CHANGELOG.txt
LICENSE.txt
MANIFEST.in
README.txt
setup.cfg
setup.py
SiteTool.egg-info/PKG-INFO
SiteTool.egg-info/SOURCES.txt
SiteTool.egg-info/dependency_links.txt
SiteTool.egg-info/entry_points.txt
SiteTool.egg-info/not-zip-safe
SiteTool.egg-info/requires.txt
SiteTool.egg-info/top_level.txt
doc/index.txt
sitetool/__init__.py
sitetool/api.py
sitetool/command.py
sitetool/exception.py
sitetool/help.py
sitetool/convert/__init__.py
sitetool/convert/blog.py
sitetool/convert/plugin.py
sitetool/convert/rst.py
sitetool/convert/suunto.py
sitetool/export/__init__.py
sitetool/export/wordpress.py
sitetool/template/__init__.py
sitetool/template/dreamweaver.py