Metadata-Version: 1.0
Name: SiteTool
Version: 0.3.0
Summary: Tools for working with HTML pages in the context of managing a website.
Home-page: http://jimmyg.org/work/code/sitetool/index.html
Author: James Gardner
Author-email: UNKNOWN
License: GPLv3
Platform: UNKNOWN
